mathics3_module_pyicu-9.0.0.dist-info/licenses/LICENSE
pymathics/icu/__init__.py
pymathics/icu/__main__.py
pymathics/icu/version.py
pymathics/language/__init__.py
pymathics/language/__main__.py
pymathics/language/version.py
mathics3_module_pyicu-9.0.0.dist-info/METADATA
mathics3_module_pyicu-9.0.0.dist-info/WHEEL
mathics3_module_pyicu-9.0.0.dist-info/top_level.txt
mathics3_module_pyicu-9.0.0.dist-info/RECORD
