Metadata-Version: 2.4
Name: Mathics3-Module-PyICU
Version: 9.0.0
Summary: Mathics3 Hello, World! module
Maintainer-email: Mathics Group <mathics-devel@googlegroups.com>
License-Expression: GPL-3.0-or-later
Project-URL: Homepage, https://github.com/Mathics3/Mathics3-Module-PyICU
Project-URL: Downloads, https://github.com/Mathics3/Mathics-Module-PyICU/releases
Keywords: Mathematica,Wolfram,Interpreter,Shell,Math,CAS
Classifier: Intended Audience :: Developers
Classifier: Intended Audience :: Science/Research
Classifier: Programming Language :: Python
Classifier: Programming Language :: Python :: 3.10
Classifier: Programming Language :: Python :: 3.11
Classifier: Programming Language :: Python :: 3.12
Classifier: Programming Language :: Python :: 3.13
Classifier: Programming Language :: Python :: Implementation :: CPython
Classifier: Programming Language :: Python :: Implementation :: PyPy
Classifier: Topic :: Scientific/Engineering
Classifier: Topic :: Scientific/Engineering :: Mathematics
Classifier: Topic :: Software Development :: Interpreters
Requires-Python: >=3.10
License-File: LICENSE
Requires-Dist: Mathics3-Module-Base>=9.0.0
Requires-Dist: Mathics3>=9.0.0
Requires-Dist: PyICU>=2.9
Provides-Extra: dev
Requires-Dist: pytest; extra == "dev"
Dynamic: license-file
